otai_base/__init__.py
otai_base/base_plugin.py
otai_base/pipes/__init__.py
otai_base/pipes/classification_pipe.py
otai_base/pipes/composite_pipe.py
otai_base/pipes/expression_pipe.py
otai_base/pipes/interval_trigger_pipe.py
otai_base/pipes/orchestrators/__init__.py
otai_base/pipes/orchestrators/simple_sequential_orchestrator.py
otai_base/pipes/pipe_runners/__init__.py
otai_base/pipes/pipe_runners/simple_sequential_runner.py
otai_base/pipes/ticket_system_pipes/__init__.py
otai_base/pipes/ticket_system_pipes/add_note_pipe.py
otai_base/pipes/ticket_system_pipes/fetch_tickets_pipe.py
otai_base/pipes/ticket_system_pipes/ticket_system_pipe.py
otai_base/pipes/ticket_system_pipes/update_ticket_pipe.py
otai_base/template_renderers/__init__.py
otai_base/template_renderers/jinja_renderer.py
otai_base/template_renderers/jinja_renderer_extras.py
otai_base-1.5.14.dist-info/METADATA
otai_base-1.5.14.dist-info/WHEEL
otai_base-1.5.14.dist-info/entry_points.txt
otai_base-1.5.14.dist-info/top_level.txt
otai_base-1.5.14.dist-info/RECORD
