Metadata-Version: 2.4
Name: otai-base
Version: 1.5.14
Summary: Base package with core implementations for Open Ticket AI - ticket system automation and AI integration
Author-email: Tobias Bück <tab@softoft.de>
Maintainer-email: Tobias Bück <tab@softoft.de>
License: LGPL-2.1-only
Project-URL: Homepage, https://open-ticket-ai.com
Project-URL: Repository, https://github.com/Softoft-Orga/open-ticket-ai
Project-URL: Source Code, https://github.com/Softoft-Orga/open-ticket-ai/tree/main/packages/otai_base
Project-URL: Documentation, https://open-ticket-ai.com
Project-URL: Issue Tracker, https://github.com/Softoft-Orga/open-ticket-ai/issues
Project-URL: Changelog, https://github.com/Softoft-Orga/open-ticket-ai/blob/main/packages/otai_base/CHANGELOG.md
Keywords: open-ticket-ai,otai,ticket-system,helpdesk,automation,ai,machine-learning,ticketing,itsm,service-desk
Classifier: Development Status :: 4 - Beta
Classifier: Intended Audience :: Developers
Classifier: Intended Audience :: Information Technology
Classifier: Intended Audience :: System Administrators
Classifier: License :: OSI Approved :: GNU Lesser General Public License v2 (LGPLv2)
Classifier: Operating System :: OS Independent
Classifier: Programming Language :: Python :: 3
Classifier: Programming Language :: Python :: 3.13
Classifier: Programming Language :: Python :: 3.14
Classifier: Topic :: Software Development :: Libraries :: Python Modules
Classifier: Topic :: System :: Systems Administration
Classifier: Topic :: Scientific/Engineering :: Artificial Intelligence
Classifier: Framework :: Pydantic
Classifier: Framework :: Pydantic :: 2
Requires-Python: >=3.13
Requires-Dist: open-ticket-ai<2.0.0,>=1.0.0
Requires-Dist: pydantic>=2.11.7
Requires-Dist: jinja2>=3.1.0
Provides-Extra: dev
Requires-Dist: pytest>=8.4.0; extra == "dev"
Requires-Dist: pytest-asyncio>=0.24.0; extra == "dev"
Requires-Dist: ruff; extra == "dev"
Requires-Dist: mypy; extra == "dev"
